paka.feedgenerator-1.5.0-py3.5-nspkg.pth
paka/feedgenerator/__init__.py
paka/feedgenerator/utils/__init__.py
paka/feedgenerator/utils/datetime_safe.py
paka/feedgenerator/utils/encoding.py
paka/feedgenerator/utils/timezone.py
paka/feedgenerator/utils/xmlutils.py
paka.feedgenerator-1.5.0.dist-info/DESCRIPTION.rst
paka.feedgenerator-1.5.0.dist-info/METADATA
paka.feedgenerator-1.5.0.dist-info/RECORD
paka.feedgenerator-1.5.0.dist-info/WHEEL
paka.feedgenerator-1.5.0.dist-info/metadata.json
paka.feedgenerator-1.5.0.dist-info/namespace_packages.txt
paka.feedgenerator-1.5.0.dist-info/top_level.txt
